datafit/__init__.py
datafit/datafit.py
datafit-0.2023.3.0.dist-info/LICENSE
datafit-0.2023.3.0.dist-info/METADATA
datafit-0.2023.3.0.dist-info/WHEEL
datafit-0.2023.3.0.dist-info/top_level.txt
datafit-0.2023.3.0.dist-info/RECORD
