Metadata-Version: 2.1
Name: datafit
Version: 0.2023.3.0
Summary: This is a Python package that automates the data preprocessing
Home-page: https://github.com/SyabAhmad/datafit
Author: Naeem Ullah, Syed Syab, Hamza Rustam
License: MIT
Classifier: Development Status :: 3 - Alpha
Classifier: Intended Audience :: Developers
Classifier: License :: OSI Approved :: MIT License
Classifier: Programming Language :: Python :: 3
Classifier: Programming Language :: Python :: 3.6
Classifier: Programming Language :: Python :: 3.7
Classifier: Programming Language :: Python :: 3.11
License-File: LICENSE
Requires-Dist: numpy>=1.0
Requires-Dist: pandas>=1.0
Requires-Dist: scikit-learn
Requires-Dist: nltk
Requires-Dist: imbalanced-learn
